{
  "id": "module",
  "statements": [
    {
      "id": "struct",
      "title": "school",
      "properties": [
        {
          "type": "string",
          "title": "name",
          "line": 3
        },
        {
          "type": "logic",
          "title": "private",
          "line": 4
        },
        {
          "type": "integer",
          "title": "type",
          "line": 5
        }
      ]
    },
    {
      "id": "def",
      "elements": [
        {
          "type": "list",
          "title": "list_of_schools",
          "line": 10
        }
      ],
      "line": 10
    },
    {
      "id": "array",
      "title": "list",
      "element_type": "school",
      "from": "1",
      "to": "9",
      "line": 8
    }
  ],
  "line": 10
}